kevo/__init__.py
kevo/client.py
kevo/connection.py
kevo/errors.py
kevo/models.py
kevo/options.py
kevo/proto/__init__.py
kevo/proto/kevo/__init__.py
kevo/proto/kevo/service_pb2.py
kevo/proto/kevo/service_pb2_grpc.py
kevo/scanner.py
kevo/transaction.py
python_kevo-0.3.2.dist-info/LICENSE
python_kevo-0.3.2.dist-info/METADATA
python_kevo-0.3.2.dist-info/WHEEL
python_kevo-0.3.2.dist-info/RECORD
