Metadata-Version: 2.3
Name: python-kevo
Version: 0.3.2
Summary: Python SDK for Kevo key-value store
License: MIT
Keywords: kevo,key-value,database
Author: Jeremy Tregunna
Author-email: jeremy@tregunna.ca
Maintainer: Kevo Team
Maintainer-email: info@example.com
Requires-Python: >=3.8
Classifier: Programming Language :: Python :: 3
Classifier: License :: OSI Approved :: MIT License
Classifier: Operating System :: OS Independent
Classifier: Development Status :: 3 - Alpha
Provides-Extra: dev
Requires-Dist: black (>=24.3.0) ; extra == "dev"
Requires-Dist: grpc-stubs (>=1.53.0) ; extra == "dev"
Requires-Dist: grpcio (>=1.59.0)
Requires-Dist: grpcio-tools (>=1.59.0)
Requires-Dist: isort (>=5.12.0) ; extra == "dev"
Requires-Dist: mypy (>=1.5.1) ; extra == "dev"
Requires-Dist: protobuf (>=4.24.0)
Requires-Dist: pylint (>=2.17.5) ; extra == "dev"
Requires-Dist: pytest (>=7.4.0) ; extra == "dev"
Project-URL: Homepage, https://github.com/KevoDB/python-sdk
Project-URL: Repository, https://github.com/KevoDB/python-sdk
